sequencetools/__init__.py
sequencetools/__main__.py
sequencetools/version.py
sequencetools/helpers/file_helpers.py
sequencetools/helpers/sequence_helpers.py
sequencetools/test_sequence/GCF_000008565.1_ASM856v1_rna_from_genomic.fna.gz
sequencetools/test_sequence/test_targets.txt
sequencetools/tools/basic_fasta_stats.py
sequencetools/tools/chunk_fasta.py
sequencetools/tools/chunk_fastq.py
sequencetools/tools/detect_chimeric_alignments.py
sequencetools/tools/fastx_converter.py
sequencetools/tools/filter_fasta_by_length.py
sequencetools/tools/format_fasta.py
sequencetools/tools/get_fasta_by_id.py
sequencetools/tools/get_fastq_by_id.py
sequencetools/tools/subset_fastq.py
sequencetools-0.0.5.dist-info/LICENSE.txt
sequencetools-0.0.5.dist-info/METADATA
sequencetools-0.0.5.dist-info/WHEEL
sequencetools-0.0.5.dist-info/entry_points.txt
sequencetools-0.0.5.dist-info/top_level.txt
sequencetools-0.0.5.dist-info/RECORD
