Metadata-Version: 2.1
Name: sequencetools
Version: 0.0.5
Summary: sequencetools -- A package for FASTX stats generation and manipulation
Home-page: https://github.com/ncgr/seqtools2.git
Author: Connor Cameron
Author-email: ctc@ncgr.org
Maintainer: Connor Cameron
Maintainer-email: ctc@ncgr.org
License: BSD 3-Clause
Keywords: science,biology,bioinformatics
Platform: UNKNOWN
Classifier: Development Status :: 4 - Beta
Classifier: Environment :: Console
Classifier: Intended Audience :: Science/Research
Classifier: License :: OSI Approved :: BSD License
Classifier: Operating System :: MacOS :: MacOS X
Classifier: Operating System :: POSIX :: Linux
Classifier: Operating System :: POSIX :: BSD
Classifier: Programming Language :: Python :: 3.4
Classifier: Programming Language :: Python :: 3.5
Classifier: Programming Language :: Python :: 3.6
Classifier: Topic :: Scientific/Engineering :: Bio-Informatics
Requires-Dist: biopython
Requires-Dist: click
Requires-Dist: intervaltree
Requires-Dist: numpy
Requires-Dist: sortedcontainers
Provides-Extra: all
Provides-Extra: docs
Requires-Dist: Sphinx (>=1.4.2) ; extra == 'docs'
Provides-Extra: tests
